Workbook

Sheet NanoPik Five Year NI Statement
B2: NanoShine Consolidated Statement of Comprehensive Income
B3: (dollars)
B4: Years ended December 31,
B5: Income Statement | D5: Year
D6: 1 | E6: 2 | F6: 3 | G6: 4 | H6: 5 | I6: 6
B7: Gross Sales | D7: =D8+D9+D10 -> 0 | E7: =SUM(E8:E10) -> 277900 | F7: =F8+F9+F10 -> 277900 | G7: =G8+G9+G10 -> 555800 | H7: =H8+H9+H10 -> 5631955 | I7: =I8+I9+I10 -> 21138320 | K7: Customer/Unit Totals | N7: % TAM (US) | O7: TAM (US)
B8: Revenue - Target Market One | D8: =D46*D51 -> 0 | E8: =E46*E51 -> 277900 | F8: =F46*F51 -> 277900 | G8: =G46*G51 -> 555800 | H8: =H46*H51 -> 555800 | I8: =I46*I51 -> 833700 | K8: Total Target Market One | M8: =I54 -> 198500 | N8: =M8/O8 -> 0.1 | O8: =1985000 -> 1985000
B9: Revenue - Target Market Two | D9: =D58*D63 -> 0 | E9: =E58*E63 -> 0 | F9: =F58*F63 -> 0 | G9: =G58*G63 -> 0 | H9: =H58*H63 -> 5076155 | I9: =I58*I63 -> 20304620 | K9: Total Units Sold - Target Market One | M9: =M8*D52 -> 198500 | N9: =M9/O9 -> 0.1 | O9: =I52*O8 -> 1985000
B10: Revenue - Target Market Three | D10: =D70*D75 -> 0 | E10: =E70*E75 -> 0 | F10: =F70*F75 -> 0 | G10: =G70*G75 -> 0 | H10: =H70*H75 -> 0 | I10: =I70*I75 -> 0 | K10: Total Target Market Two | M10: =I66 -> 4350990 | N10: =M10/O10 -> 0.013144985 | O10: 331000000 | P10: 16
B11: Total Cost of goods sold | D11: =D12+D13+D14 -> 0 | E11: =E12+E13+E14 -> 214380 | F11: =F12+F13+F14 -> 214380 | G11: =G12+G13+G14 -> 397000 | H11: =H12+H13+H14 -> 3218260 | I11: =I12+I13+I14 -> 11475088 | K11: Total Units Sold - Target Market Two | M11: =M10*I64 -> 4350990 | N11: =M11/O11 -> 0.013144985 | O11: =O10*I64 -> 331000000
B12: Cost of Goods Sold - Target Market One | D12: =D48*D51 -> 0 | E12: =E48*E51 -> 214380 | F12: =F48*F51 -> 214380 | G12: =G48*G51 -> 397000 | H12: =H48*H51 -> 317600 | I12: =I48*I51 -> 452580 | K12: Total Target Market Three | M12: =I78 | N12: =M12/O12 -> #DIV/0!
B13: Cost of Goods Sold - Target Market Two | D13: =D60*D63 -> 0 | E13: =E60*E63 -> 0 | F13: =F60*F63 -> 0 | G13: =G60*G63 -> 0 | H13: =H60*H63 -> 2900660 | I13: =I60*I63 -> 11022508 | K13: Total Units Sold - Target Market Three | M13: =M12*D76 -> 0 | N13: =M13/O13 -> #DIV/0! | O13: =O12*D76 -> 0
B14: Cost of Goods Sold - Target Market Three | D14: =D72*D75 -> 0 | E14: =E72*E75 -> 0 | F14: =F72*F75 -> 0 | G14: =G72*G75 -> 0 | H14: =H72*H75 -> 0 | I14: =I72*I75 -> 0 | K14: Total Units Sold | M14: =M9+M11+M13 -> 4549490 | N14: =M14/O14 -> 0.013662748 | O14: =O9+O11+O13 -> 332985000
B15: Gross Profit | D15: =D7-D11 -> 0 | E15: =E7-E11 -> 63520 | F15: =F7-F11 -> 63520 | G15: =G7-G11 -> 158800 | H15: =H7-H11 -> 2413695 | I15: =I7-I11 -> 9663232
B16: Gross Margins | D16: 0 | E16: =E15/E7 -> 0.22857143 | F16: =F15/F7 -> 0.22857143 | G16: =G15/G7 -> 0.28571429 | H16: =H15/H7 -> 0.42857143 | I16: =I15/I7 -> 0.45714286
B17: Setup Expenses | D17: =17500 -> 17500 | F17: 0 | G17: 0 | H17: 0 | I17: 0 | J17: 7
B18: Research and Development | D18: 0 | E18: =E7*$E$37 -> 5432.945 | F18: =F7*$E$37 -> 5432.945 | G18: =G7*$E$37 -> 10865.89 | H18: =H7*$E$37 -> 110104.72 | I18: =I7*$E$37 -> 413254.16
B19: Selling, General and Administrative Expense | D19: =2*E19 -> 120608.6 | E19: =E7*$E$38 -> 60304.3 | F19: =F7*$E$38 -> 60304.3 | G19: =G7*$E$38 -> 120608.6 | H19: =H7*$E$38 -> 1222134.2 | I19: =I7*$E$38 -> 4587015.4
B20: Other Revenue (Expenses)
B21: Royalty Payments | C21: 0 | D21: =$C$21*D7 -> 0 | E21: =$C$21*E7 -> 0 | F21: =$C$21*F7 -> 0 | G21: =$C$21*G7 -> 0 | H21: =$C$21*H7 -> 0 | I21: =$C$21*I7 -> 0
B22: Commission | C22: 0.225 | D22: =D7*$C$22 -> 0 | E22: =E7*$C$22 -> 62527.5 | F22: =F7*$C$22 -> 62527.5 | G22: =G7*$C$22 -> 125055 | H22: =H7*$C$22 -> 1267189.9 | I22: =I7*$C$22 -> 4756122 | J22: 5
B23: Trials | D23: 0
B24: EBITDA | D24: =D7-D11-D18-D19-D21 -> -120608.6 | E24: =E7-E11-E18-E19-E21 -> -2217.245 | F24: =F7-F11-F18-F19-F21 -> -2217.245 | G24: =G7-G11-G18-G19-G21 -> 27325.51 | H24: =H7-H11-H18-H19-H21 -> 1081456 | I24: =I7-I11-I18-I19-I21 -> 4662962.4
B25: Depreciation and Amortization | D25: =D39*D7 -> 0 | E25: =E39*E7 -> 8337 | F25: =F39*F7 -> 8337 | G25: =G39*G7 -> 16674 | H25: =H39*H7 -> 168958.65 | I25: =I39*I7 -> 634149.6
B26: EBIT | D26: =D24+D25 -> -120608.6 | E26: =E24-E25 -> -10554.245 | F26: =F24-F25 -> -10554.245 | G26: =G24-G25 -> 10651.51 | H26: =H24-H25 -> 912497.39 | I26: =I24-I25 -> 4028812.8
B27: Interest Exp | C27: 0.006 | E27: =$C$27*E7 -> 1667.4 | F27: =$C$27*F7 -> 1667.4 | G27: =$C$27*G7 -> 3334.8 | H27: =$C$27*H7 -> 33791.73 | I27: =$C$27*I7 -> 126829.92 | J27: 6
B28: Pre-Tax Income | D28: =D26-D27 -> -120608.6 | E28: =E26-E27 -> -12221.645 | F28: =F26-F27 -> -12221.645 | G28: =G26-G27 -> 7316.71 | H28: =H26-H27 -> 878705.66 | I28: =I26-I27 -> 3901982.9
B29: Taxes | D29: 0 | E29: =E28*$E$40 -> -2566.5455 | F29: =F28*$E$40 -> -2566.5455 | G29: =G28*$E$40 -> 1536.5091 | H29: =H28*$E$40 -> 184528.19 | I29: =I28*$E$40 -> 819416.41
B30: Net Income | D30: =D28-D29 -> -120608.6 | E30: =E28-E29 -> -9655.0996 | F30: =F28-F29 -> -9655.0996 | G30: =G28-G29 -> 5780.2009 | H30: =H28-H29 -> 694177.48 | I30: =I28-I29 -> 3082566.5
B32: Unit Price | D32: =D46 -> 7 | E32: =E46 -> 7 | F32: =F46 -> 7 | G32: =G46 -> 7 | H32: =H46 -> 7 | I32: =I46 -> 7
B33: Unit Cost | D33: =D48 -> 5.4 | E33: =E48 -> 5.4 | F33: =F48 -> 5.4 | G33: =G48 -> 5 | H33: =H48 -> 4 | I33: =I48 -> 3.8
B35: Total No. of Units Sold per year | D35: =D51+D63+D75 -> 0 | F35: =F51+F63+F75 -> 39700 | G35: =G51+G63+G75 -> 79400 | H35: =H51+H63+H75 -> 804565 | I35: =I51+I63+I75 -> 3019760
B37: Research and Development | D37: 0.01955 | E37: 0.01955 | F37: 0.01955 | G37: 0.01955 | H37: 0.01955 | I37: 0.01955 | J37: 2
B38: Selling, General and Administrative | D38: 0.217 | E38: 0.217 | F38: 0.217 | G38: 0.217 | H38: 0.217 | I38: 0.217 | J38: 3
B39: Depreciation and Amortization | D39: 0.03 | E39: 0.03 | F39: 0.03 | G39: 0.03 | H39: 0.03 | I39: 0.03 | J39: 4
B40: Taxes | D40: 0.21 | E40: 0.21 | F40: 0.21 | G40: 0.21 | H40: 0.21 | I40: 0.21
B42: Revenue Assumptions | C42: Year
B43: Category | C43: 0 | D43: 1 | E43: 2 | F43: 3 | G43: 4 | H43: 5 | I43: 6
B44: Total Penetration - WaterPik | D44: 0 | E44: 0.02 | F44: 0.04 | G44: 0.06 | H44: 0.08 | I44: 0.1 | J44: 13
B45: Growth Rate | F45: =F53/E53 -> 1 | G45: =G53/F53 -> 2 | H45: =H53/G53 -> 1 | I45: =I53/H53 -> 1.5
B46: Unit Price - Target Market One | D46: 7 | E46: 7 | F46: 7 | G46: 7 | H46: 7 | I46: 7
B47: Unit Price Growth Rate
B48: Unit Cost - Target Market One | D48: 5.4 | E48: 5.4 | F48: 5.4 | G48: 5 | H48: 4 | I48: 3.8 | J48: 11
B49: Unit Cost Growth Rate
B50: Unit Gross Margins - Target Market One | D50: =(D46-D48)/D46 -> 0.22857143 | E50: =(E46-E48)/E46 -> 0.22857143 | F50: =(F46-F48)/F46 -> 0.22857143 | G50: =(G46-G48)/G46 -> 0.28571429 | H50: =(H46-H48)/H46 -> 0.42857143 | I50: =(I46-I48)/I46 -> 0.45714286 | J50: 1
B51: Devices Sold - Target Market One | D51: 0 | E51: =E52*E53 -> 39700 | F51: =F52*F53 -> 39700 | G51: =G52*G53 -> 79400 | H51: =H52*H53 -> 79400 | I51: =I52*I53 -> 119100
B52: Avg Devices Sold Per Target Market One | D52: 1 | E52: 1 | F52: 1 | G52: 1 | H52: 1 | I52: 1 | J52: 14
B53: Number of Customers - Target Market One | D53: 0 | E53: =E54-D53 -> 39700 | F53: =F54-E53 -> 39700 | G53: =G54-F53 -> 79400 | H53: =H54-G53 -> 79400 | I53: =I54-H53 -> 119100 | J53: 12
B54: Cumulative Target Market One | D54: 0 | E54: =1985000*E44 -> 39700 | F54: =1985000*F44 -> 79400 | G54: =1985000*G44 -> 119100 | H54: =1985000*H44 -> 158800 | I54: =1985000*I44 -> 198500
B56: Total Penetration -Dentists & Hygienists | G56: =G66/$O$10 -> 0.0021908308 | H56: =H66/$O$10 -> 0.0043816616 | I56: =I66/$O$10 -> 0.013144985 | J56: 8
B57: Growth Rate | H57: =H65/G65 -> 1 | I57: =I65/H65 -> 4 | J57: 9
B58: Unit Price - Target Market Two | G58: 7 | H58: 7 | I58: 7
B59: Unit Price Growth Rate
B60: Unit Cost - Target Market Two | G60: 5 | H60: 4 | I60: 3.8
B61: Unit Cost Growth Rate
B62: Unit Gross Margins - Target Market Two | G62: =(G58-G60)/G58 -> 0.28571429 | H62: =(H58-H60)/H58 -> 0.42857143 | I62: =(I58-I60)/I58 -> 0.45714286
B63: Devices Sold - Target Market Two | H63: =H64*H65 -> 725165 | I63: =I64*I65 -> 2900660
B64: Avg Devices Sold per Target Market Two | G64: 1 | H64: 1 | I64: 1 | J64: 15
B65: Number of Customers - Target Market Two | G65: =(207190*0.01)/2*3500*0.2 -> 725165 | H65: =(207190*0.01)/2*3500*0.2 -> 725165 | I65: =207190*0.01*3500*0.2*2 -> 2900660 | J65: 10
B66: Cumulative Target Market Two | G66: =F66+G65 -> 725165 | H66: =G66+H65 -> 1450330 | I66: =H66+I65 -> 4350990
B68: Total Penetration - Target Market Three
B69: Growth Rate
B70: Unit Price - Target Market Three
B71: Unit Price Growth Rate
B72: Unit Cost - Target Market Three
B73: Unit Cost Growth Rate
B74: Unit Gross Margins - Target Market Three
B75: Devices Sold - Target Market Three
B76: Avg Devices Sold per Target Market Three
B77: Number of Customers - Target Market Three
B78: Cumulative Target Market Three

Sheet Key Assumptions
A1: 1 | B1: Latest F/S can be found for waterpik before it was acquired was for 2003, 2004, 2005. The profit margin was around 30%. WaterPik's parent company has a profit margin of around 42% in 2022. Since we position the NanoPik as a premium product offering a better oral hygiene solution, we expect a slightly higher margin (in the higher 40%).
A2: 2 | B2: Latest F/S can be found for waterpik before it was acquired was for 2003, 2004, 2005. The comparative R&D percentages were 1.762%, 1.938%, 2.166%). Three year average of R&D investment is 2.955% | P2: https://www.sec.gov/Archives/edgar/vprr/0602/06025941.pdf
A3: 3 | B3: Latest F/S can be found for waterpik before it was acquired was for 2003, 2004, 2005. The comparative SG&A percentages were 20.5%, 21.77%, 22.84%). Three year average of R&D investment is 21.7%
A4: 4 | B4: The primary depreciable asset would be the patent for the nanopik technology. We have referred one of Waterpik's key competitors, Philips Sonicare, for a depreciation and amortization percentage, which is 3%. | Q4: file:///Users/wangmandi/Downloads/PhilipsFullAnnualReport2022-English.pdf | W4: page 32
A5: 5 | B5: Third party normally charges a commision ranging between 15% to 30%. We take the average and say we will give WaterPik 22.5% of the revenue. | L5: https://backofhouse.io/stories/tips-navigate-negotiate-restaurant-contracts-third-party-food-delivery-platforms-commission-rates
A6: 6 | B6: Latest F/S can be found for waterpik before it was acquired was for 2003, 2004, 2005. The comparative interest expense percentages were 0.48%, 0.55%, 0.77%). Three year average of R&D investment is 0.6%
A7: 7 | B7: In the first year, the set up cost is mainly comprised of the patent cost. The average cost to obtain a patent is between $15,000 to $20,000. We took the average of that and concludes that our setup cost is $17,500. We do not think we will incur any costs to start production because WaterPik can provide us with the production capacity. We recognize that the first year SG&A costs would be high as we are negotiating the partnership deal with WaterPik. We estimate that it would be twice the SG&A cost in year 2. | AM7: https://www.bitlaw.com/guidance/patent/what-does-a-patent-application-cost.html
A8: 8 | B8: Our secondary market would be the dentists and hygienists, who will recommend NanoPik to patients during their visits. We think it only makes sense to enter this market after the cost of production decreases with economies of scale. There are currently 207190 active hygienists in the United States. We estimate that 1% of them are KOLs. We plan to reach half of them in year3, which is 0.05% of the total US hygienists. | AE8: https://www.bls.gov/oes/current/oes291292.htm
A9: 9 | B9: We used the most conservative estimate, presuming that each KOL would talk one hygienist/dentist into recommending NanoPik each year.
A10: 10 | B10: On average, each dentist/hygienist treats around 3500 patients each year. Dentist referral success rate is around 30%. Given that NanoPik is a relatively new product, the referral success rate would be lower than mature oral hygiene products. That means each KOL can convince 700 patients to try the NanoPik product. | P10: https://www.statista.com/statistics/965365/patient-visits-among-all-dentists-us-per-year/ | W10: https://pubmed.ncbi.nlm.nih.gov/33210783/
A11: 11 | B11: We referenced to a typical mouthwash company since we are only producing the solution. According to IBIS, COGS for mouthwash manugacturers is around 50%. For a 1L mouthwash product (such as Listerine), the production cost would be $9*50%=$4.5. Our Nanoparticle would only account for 10% of the 1L solution, which would cost $4.5*10%=0.45 to produce. Each customer woule need 12 of those 1L solutions each year, which means the production cost is around $0.45*12=$5.4
A12: 12 | B12: According to Factset, the estimated revenue for WaterPik was $198.5 million. It's also a reasonable amount given that WaterPik had 70% of its revenue relates to water flosser market in 2017 (before it was acquired by Church & Dwlight), which is around $185.5 million. On average, a WaterPik product costs $100. We estimate that 1.985 million units of water flosser are sold. WaterPik had around 1.985 million water flosser customers in 2022. | AK12: https://my-ibisworld-com.libproxy2.usc.edu/us/en/industry-specialized/od6033/key-statistics | AL12: https://www.businesswire.com/news/home/20170717005482/en/Church-Dwight-to-Acquire-Waterpik-for-Approximately-1-Billion
A13: 13 | B13: On average, consumer products have a penetration rate of 2%-6%. We think that we are targeting a very small and niched market, and we are partnering directly with WaterPik to advertise our product, we can ultimately achieve a higher penetration rate of 10%. | T13: https://gocardless.com/en-us/guides/posts/market-penetration/#:~:text=market%20penetration%205%25.-,What%20is%20a%20good%20rate%20of%20market%20penetration%3F,already%20doing%20better%20than%20most
A14: 14 | B14: A 1.5 L of LIsterine mouthwash can last around a month. Based on that we estimate that customers would purchase 12 bottles of 1.5 L solution containing nanoparticles each year. | Z14: https://www.quora.com/Does-a-1-5-liter-Listerine-mouthwash-last-for-about-2-months-if-used-every-day
A15: 15 | B15: In our interviews, we found out that most people visit dentists once per year.
A16: 16 | B16: The TAM for market 2 would be the US population, which is around 331 million people.

Sheet Graph table
C3: 1 | D3: 2 | E3: 3 | F3: 4 | G3: 5 | H3: 6
B4: Gross Sales | C4: ='NanoPik Five Year NI Statement'!D7 -> 0 | D4: ='NanoPik Five Year NI Statement'!E7 -> 277900 | E4: ='NanoPik Five Year NI Statement'!F7 -> 277900 | F4: ='NanoPik Five Year NI Statement'!G7 -> 555800 | G4: ='NanoPik Five Year NI Statement'!H7 -> 5631955 | H4: ='NanoPik Five Year NI Statement'!I7 -> 21138320
B5: Total Cost of goods sold | C5: ='NanoPik Five Year NI Statement'!D11 -> 0 | D5: ='NanoPik Five Year NI Statement'!E11 -> 214380 | E5: ='NanoPik Five Year NI Statement'!F11 -> 214380 | F5: ='NanoPik Five Year NI Statement'!G11 -> 397000 | G5: ='NanoPik Five Year NI Statement'!H11 -> 3218260 | H5: ='NanoPik Five Year NI Statement'!I11 -> 11475088
B6: Gross Profit | C6: ='NanoPik Five Year NI Statement'!D15 -> 0 | D6: ='NanoPik Five Year NI Statement'!E15 -> 63520 | E6: ='NanoPik Five Year NI Statement'!F15 -> 63520 | F6: ='NanoPik Five Year NI Statement'!G15 -> 158800 | G6: ='NanoPik Five Year NI Statement'!H15 -> 2413695 | H6: ='NanoPik Five Year NI Statement'!I15 -> 9663232
B7: EBITDA | C7: ='NanoPik Five Year NI Statement'!D24 -> -120608.6 | D7: ='NanoPik Five Year NI Statement'!E24 -> -2217.245 | E7: ='NanoPik Five Year NI Statement'!F24 -> -2217.245 | F7: ='NanoPik Five Year NI Statement'!G24 -> 27325.51 | G7: ='NanoPik Five Year NI Statement'!H24 -> 1081456 | H7: ='NanoPik Five Year NI Statement'!I24 -> 4662962.4
B8: Net Income | C8: ='NanoPik Five Year NI Statement'!D30 -> -120608.6 | D8: ='NanoPik Five Year NI Statement'!E30 -> -9655.0996 | E8: ='NanoPik Five Year NI Statement'!F30 -> -9655.0996 | F8: ='NanoPik Five Year NI Statement'!G30 -> 5780.2009 | G8: ='NanoPik Five Year NI Statement'!H30 -> 694177.48 | H8: ='NanoPik Five Year NI Statement'!I30 -> 3082566.5

Sheet Sample
B2: Sample Income Statement for Sale of Product One
B3: Note: All numbers are for demonstration only and do not reflect the actual market, sales price, cost of goods sold, or other inputs or %
B5: Income Statement | D5: Year
D6: 1 | E6: 2 | F6: 3 | G6: 4 | H6: 5 | I6: 6
B7: Gross Sales | D7: =D8+D9+D10 -> 0 | E7: =E8+E9+E10 -> 6800000 | F7: =F8+F9+F10 -> 6112500 | G7: =G8+G9+G10 -> 10605000 | H7: =H8+H9+H10 -> 15568875 | I7: =I8+I9+I10 -> 32761969 | K7: Customer/Unit Totals | N7: % TAM (US) | O7: TAM (US)
B8: Revenue - Target Market One | D8: =D46*D51 -> 0 | E8: =E46*E51 -> 2400000 | F8: =F46*F51 -> 2025000 | G8: =G46*G51 -> 3240000 | H8: =H46*H51 -> 4536000 | I8: =I46*I51 -> 9072000 | K8: Total Target Market One | M8: =I54 -> 262.05 | N8: =M8/O8 -> 0.08735 | O8: 3000
B9: Revenue - Target Market Two | D9: =D58*D63 -> 0 | E9: =E58*E63 -> 2400000 | F9: =F58*F63 -> 2025000 | G9: =G58*G63 -> 3240000 | H9: =H58*H63 -> 4536000 | I9: =I58*I63 -> 9072000 | K9: Total Units Sold - Target Market One | M9: =M8*D52 -> 524.1 | N9: =M9/O9 -> 0.08735 | O9: =O8*D52 -> 6000
B10: Revenue - Target Market Three | D10: =D70*D75 -> 0 | E10: =E70*E75 -> 2000000 | F10: =F70*F75 -> 2062500 | G10: =G70*G75 -> 4125000 | H10: =H70*H75 -> 6496875 | I10: =I70*I75 -> 14617969 | K10: Total Target Market Two | M10: =I66 -> 262.05 | N10: =M10/O10 -> 0.043675 | O10: 6000
B11: Total Cost of goods sold | D11: =D12+D13+D14 -> 0 | E11: =E12+E13+E14 -> 4250000 | F11: =F12+F13+F14 -> 3667500 | G11: =G12+G13+G14 -> 6363000 | H11: =H12+H13+H14 -> 6672375 | I11: =I12+I13+I14 -> 14040844 | K11: Total Units Sold - Target Market Two | M11: =M10*D64 -> 524.1 | N11: =M11/O11 -> 0.043675 | O11: =O10*D64 -> 12000
B12: Cost of Goods Sold - Target Market One | D12: =D48*D51 -> 0 | E12: =E48*E51 -> 1500000 | F12: =F48*F51 -> 1215000 | G12: =G48*G51 -> 1944000 | H12: =H48*H51 -> 1944000 | I12: =I48*I51 -> 3888000 | K12: Total Target Market Three | M12: =I78 -> 752.03125 | N12: =M12/O12 -> 0.050135417 | O12: 15000
B13: Cost of Goods Sold - Target Market Two | D13: =D60*D63 -> 0 | E13: =E60*E63 -> 1500000 | F13: =F60*F63 -> 1215000 | G13: =G60*G63 -> 1944000 | H13: =H60*H63 -> 1944000 | I13: =I60*I63 -> 3888000 | K13: Total Units Sold - Target Market Three | M13: =M12*D76 -> 752.03125 | N13: =M13/O13 -> 0.050135417 | O13: =O12*D76 -> 15000
B14: Cost of Goods Sold - Target Market Three | D14: =D72*D75 -> 0 | E14: =E72*E75 -> 1250000 | F14: =F72*F75 -> 1237500 | G14: =G72*G75 -> 2475000 | H14: =H72*H75 -> 2784375 | I14: =I72*I75 -> 6264843.8 | K14: Total Units Sold | M14: =M9+M11+M13 -> 1800.2313 | N14: =M14/O14 -> 0.054552462 | O14: =O9+O11+O13 -> 33000
B15: Gross Profit | D15: =D7-D11 -> 0 | E15: =E7-E11 -> 2550000 | F15: =F7-F11 -> 2445000 | G15: =G7-G11 -> 4242000 | H15: =H7-H11 -> 8896500 | I15: =I7-I11 -> 18721125
B16: Gross Margins | D16: 0 | E16: =E15/E7 -> 0.375 | F16: =F15/F7 -> 0.4 | G16: =G15/G7 -> 0.4 | H16: =H15/H7 -> 0.57142857 | I16: =I15/I7 -> 0.57142857
B17: Setup Expenses | D17: 3000000 | E17: 1500000 | F17: 0 | G17: 0 | H17: 0 | I17: 0
B18: Research and Development | D18: 0 | E18: =E7*$E$37 -> 476000 | F18: =F7*$E$37 -> 427875 | G18: =G7*$E$37 -> 742350 | H18: =H7*$E$37 -> 1089821.2 | I18: =I7*$E$37 -> 2293337.8
B19: Selling, General and Administrative Expense | D19: 2500000 | E19: =E7*$E$38 -> 2380000 | F19: =F7*$E$38 -> 2139375 | G19: =G7*$E$38 -> 3711750 | H19: =H7*$E$38 -> 5449106.2 | I19: =I7*$E$38 -> 11466689
B20: Other Revenue (Expenses)
B21: Royalty Payments | C21: 0.08 | D21: =$C$21*D7 -> 0 | E21: =$C$21*E7 -> 544000 | F21: =$C$21*F7 -> 489000 | G21: =$C$21*G7 -> 848400 | H21: =$C$21*H7 -> 1245510 | I21: =$C$21*I7 -> 2620957.5
B22: Commission | C22: 0.05 | D22: =$C$22*D11 -> 0 | E22: =$C$22*E11 -> 212500 | F22: =$C$22*F11 -> 183375 | G22: =$C$22*G11 -> 318150 | H22: =$C$22*H11 -> 333618.75 | I22: =$C$22*I11 -> 702042.19
B23: Trials | D23: 0 | E23: 1000000 | F23: 1000000 | G23: 0 | H23: 0 | I23: 0
B24: EBITDA | D24: =D7-D11-D18-D19-D21 -> -2500000 | E24: =E7-E11-E18-E19-E21 -> -850000 | F24: =F7-F11-F18-F19-F21 -> -611250 | G24: =G7-G11-G18-G19-G21 -> -1060500 | H24: =H7-H11-H18-H19-H21 -> 1112062.5 | I24: =I7-I11-I18-I19-I21 -> 2340140.6
B25: Depreciation and Amortization | D25: 0 | E25: 0 | F25: 0 | G25: 0 | H25: 0 | I25: 0
B26: EBIT | D26: =D24+D25 -> -2500000 | E26: =E24+E25 -> -850000 | F26: =F24+F25 -> -611250 | G26: =G24+G25 -> -1060500 | H26: =H24+H25 -> 1112062.5 | I26: =I24+I25 -> 2340140.6
B27: Interest Exp | D27: 0 | E27: 0 | F27: 0 | G27: 0 | H27: 0 | I27: 0
B28: Pre-Tax Income | D28: =D26-D27 -> -2500000 | E28: =E26-E27 -> -850000 | F28: =F26-F27 -> -611250 | G28: =G26-G27 -> -1060500 | H28: =H26-H27 -> 1112062.5 | I28: =I26-I27 -> 2340140.6
B29: Taxes | D29: 0 | E29: =E28*$D$40 -> -178500 | F29: =F28*$D$40 -> -128362.5 | G29: =G28*$D$40 -> -222705 | H29: =H28*$D$40 -> 233533.12 | I29: =I28*$D$40 -> 491429.53
B30: Net Income | D30: =D28-D29 -> -2500000 | E30: =E28-E29 -> -671500 | F30: =F28-F29 -> -482887.5 | G30: =G28-G29 -> -837795 | H30: =H28-H29 -> 878529.38 | I30: =I28-I29 -> 1848711.1
B32: Unit Price | D32: 80000 | E32: 80000 | F32: 50000 | G32: 50000 | H32: 35000 | I32: 35000
B33: Unit Cost | D33: 50000 | E33: 50000 | F33: 30000 | G33: 30000 | H33: 15000 | I33: 15000
B35: Total No. of Units Sold per year | D35: =D51+D63+D75 -> 0 | E35: =E51+E63+E75 -> 85 | F35: =F51+F63+F75 -> 122.25 | G35: =G51+G63+G75 -> 212.1 | H35: =H51+H63+H75 -> 444.825 | I35: =I51+I63+I75 -> 936.05625
B37: Research and Development | D37: 0.07 | E37: 0.07 | F37: 0.07 | G37: 0.07 | H37: 0.07 | I37: 0.07
B38: Selling, General and Administrative | D38: 0.35 | E38: 0.35 | F38: 0.35 | G38: 0.35 | H38: 0.35 | I38: 0.35
B39: Depreciation and Amortization | D39: 0.15 | E39: 0.15 | F39: 0.15 | G39: 0.15 | H39: 0.15 | I39: 0.15
B40: Taxes | D40: 0.21 | E40: 0.21 | F40: 0.21 | G40: 0.21 | H40: 0.21 | I40: 0.21
B42: Revenue Assumptions | C42: Year
B43: Category | C43: 0 | D43: 1 | E43: 2 | F43: 3 | G43: 4 | H43: 5 | I43: 6
B44: Total Penetration - Target Market One | D44: 0 | E44: 0.0046765394 | F44: 0.010989867 | G44: 0.01951286 | H44: 0.033149649 | I44: 0.060423227
B45: Growth Rate | D45: 0 | E45: 0.25 | F45: 0.35 | G45: 0.35 | H45: 0.6 | I45: 1 | J45: 1
B46: Unit Price - Target Market One | D46: =D32 -> 80000 | E46: =E32 -> 80000 | F46: =F32 -> 50000 | G46: =G32 -> 50000 | H46: =H32 -> 35000 | I46: =I32 -> 35000
B47: Unit Price Growth Rate | D47: 0 | E47: 0 | F47: 0 | G47: 0 | H47: 0 | I47: 0
B48: Unit Cost - Target Market One | D48: =D33 -> 50000 | E48: =E33 -> 50000 | F48: =F33 -> 30000 | G48: =G33 -> 30000 | H48: =H33 -> 15000 | I48: =I33 -> 15000
B49: Unit Cost Growth Rate | D49: 0 | E49: 0 | F49: 0 | G49: 0 | H49: 0 | I49: 0
B50: Unit Gross Margins - Target Market One | D50: 0.5 | E50: 0.5 | F50: 0.6 | G50: 0.6 | H50: 0.7 | I50: 0.7
B51: Devices Sold - Target Market One | D51: =D52*D53 -> 0 | E51: =E52*E53 -> 30 | F51: =F52*F53 -> 40.5 | G51: =G52*G53 -> 64.8 | H51: =H52*H53 -> 129.6 | I51: =I52*I53 -> 259.2
B52: Avg Devices Sold Per Target Market One | D52: 2 | E52: 2 | F52: 2 | G52: 2 | H52: 2 | I52: 2
B53: Number of Customers - Target Market One | D53: 0 | E53: 15 | F53: =E53*(1+F45) -> 20.25 | G53: =F53*(1+H45) -> 32.4 | H53: =G53*(1+I45) -> 64.8 | I53: =H53*(1+J45) -> 129.6
B54: Cumulative Target Market One | D54: =D53 -> 0 | E54: =D54+E53 -> 15 | F54: =E54+F53 -> 35.25 | G54: =F54+G53 -> 67.65 | H54: =G54+H53 -> 132.45 | I54: =H54+I53 -> 262.05
B56: Total Penetration - Target Market Two | D56: 0 | E56: 0.002550153 | F56: 0.0059928596 | G56: 0.010640513 | H56: 0.01807676 | I56: 0.032949252
B57: Growth Rate | D57: 0 | E57: 0.25 | F57: 0.35 | G57: 0.35 | H57: 0.6 | I57: 1 | J57: 1
B58: Unit Price - Target Market Two | D58: =D32 -> 80000 | E58: =E32 -> 80000 | F58: =F32 -> 50000 | G58: =G32 -> 50000 | H58: =H32 -> 35000 | I58: =I32 -> 35000
B59: Unit Price Growth Rate | D59: 0 | E59: 0 | F59: 0 | G59: 0 | H59: 0 | I59: 0
B60: Unit Cost - Target Market Two | D60: =D33 -> 50000 | E60: =E33 -> 50000 | F60: =F33 -> 30000 | G60: =G33 -> 30000 | H60: =H33 -> 15000 | I60: =I33 -> 15000
B61: Unit Cost Growth Rate | D61: 0 | E61: 0 | F61: 0 | G61: 0 | H61: 0 | I61: 0
B62: Unit Gross Margins - Target Market Two | D62: 0.5 | E62: 0.5 | F62: 0.6 | G62: 0.6 | H62: 0.7 | I62: 0.7
B63: Devices Sold - Target Market Two | D63: =D64*D65 -> 0 | E63: =E64*E65 -> 30 | F63: =F64*F65 -> 40.5 | G63: =G64*G65 -> 64.8 | H63: =H64*H65 -> 129.6 | I63: =I64*I65 -> 259.2
B64: Avg Devices Sold per Target Market Two | D64: 2 | E64: 2 | F64: 2 | G64: 2 | H64: 2 | I64: 2
B65: Number of Customers - Target Market Two | D65: 0 | E65: 15 | F65: =E65*(1+G57) -> 20.25 | G65: =F65*(1+H57) -> 32.4 | H65: =G65*(1+I57) -> 64.8 | I65: =H65*(1+J57) -> 129.6
B66: Cumulative Target Market Two | D66: =D65 -> 0 | E66: =D66+E65 -> 15 | F66: =E66+F65 -> 35.25 | G66: =F66+G65 -> 67.65 | H66: =G66+H65 -> 132.45 | I66: =H66+I65 -> 262.05
B68: Total Penetration - Target Market Three | D68: 0 | E68: 0.0019827108 | F68: 0.0052541835 | G68: 0.010652114 | H68: 0.021447974 | I68: 0.045738659
B69: Growth Rate | D69: 0 | E69: 0.5 | F69: 0.65 | G69: 0.65 | H69: 1 | I69: 1.25 | J69: 1.25
B70: Unit Price - Target Market Three | D70: =D32 -> 80000 | E70: =E32 -> 80000 | F70: =F32 -> 50000 | G70: =G32 -> 50000 | H70: =H32 -> 35000 | I70: =I32 -> 35000
B71: Unit Price Growth Rate | D71: 0 | E71: 0 | F71: 0 | G71: 0 | H71: 0 | I71: 0
B72: Unit Cost - Target Market Three | D72: =D33 -> 50000 | E72: =E33 -> 50000 | F72: =F33 -> 30000 | G72: =G33 -> 30000 | H72: =H33 -> 15000 | I72: =I33 -> 15000
B73: Unit Cost Growth Rate | D73: 0 | E73: 0 | F73: 0 | G73: 0 | H73: 0 | I73: 0
B74: Unit Gross Margins - Target Market Three | D74: 0.5 | E74: 0.5 | F74: 0.6 | G74: 0.6 | H74: 0.7 | I74: 0.7
B75: Devices Sold - Target Market Three | D75: =D76*D77 -> 0 | E75: =E76*E77 -> 25 | F75: =F76*F77 -> 41.25 | G75: =G76*G77 -> 82.5 | H75: =H76*H77 -> 185.625 | I75: =I76*I77 -> 417.65625
B76: Avg Devices Sold per Target Market Three | D76: 1 | E76: 1 | F76: 1 | G76: 1 | H76: 1 | I76: 1
B77: Number of Customers - Target Market Three | D77: 0 | E77: 25 | F77: =E77*(1+G69) -> 41.25 | G77: =F77*(1+H69) -> 82.5 | H77: =G77*(1+I69) -> 185.625 | I77: =H77*(1+J69) -> 417.65625
B78: Cumulative Target Market Three | D78: =D77 -> 0 | E78: =D78+E77 -> 25 | F78: =E78+F77 -> 66.25 | G78: =F78+G77 -> 148.75 | H78: =G78+H77 -> 334.375 | I78: =H78+I77 -> 752.03125
